peanutbutter/__init__.py
peanutbutter/__version__.py
peanutbutter-0.1.1.dist-info/LICENSE
peanutbutter-0.1.1.dist-info/METADATA
peanutbutter-0.1.1.dist-info/WHEEL
peanutbutter-0.1.1.dist-info/top_level.txt
peanutbutter-0.1.1.dist-info/RECORD
