Metadata-Version: 2.1
Name: peanutbutter
Version: 0.1.1
Summary: Property-Based Testing and LLMS, what could go wrong?
Author-email: chrisaddy <chris.william.addy@gmail.com>
License: MIT License
Keywords: testing,LLMs
Requires-Python: >=3.10
License-File: LICENSE
Requires-Dist: instructor
Provides-Extra: dev
Requires-Dist: black ; extra == 'dev'
Requires-Dist: ruff ; extra == 'dev'
Requires-Dist: twine ; extra == 'dev'
